[
    {
        "country": "China",
        "countryInfo": {"iso2": "CN"},
        "cases": 80928,
        "todayCases": 34,
        "deaths": 3245,
        "todayDeaths": 8,
        "recovered": 70420,
        "active": 7263,
        "critical": 2274,
        "casesPerOneMillion": 56
    },
    {
        "country": "Italy",
        "countryInfo": {"iso2": "IT"},
        "cases": 41035,
        "todayCases": 5322,
        "deaths": 3405,
        "todayDeaths": 427,
        "recovered": 4440,
        "active": 33190,
        "critical": 2498,
        "casesPerOneMillion": 679
    },
    {
        "country": "Iran",
        "countryInfo": {"iso2": "IR"},
        "cases": 18407,
        "todayCases": 1046,
        "deaths": 1284,
        "todayDeaths": 149,
        "recovered": 5979,
        "active": 11144,
        "critical": 0,
        "casesPerOneMillion": 219
    },
    {
        "country": "Spain",
        "countryInfo": {"iso2": "ES"},
        "cases": 18077,
        "todayCases": 3308,
        "deaths": 831,
        "todayDeaths": 193,
        "recovered": 1107,
        "active": 16139,
        "critical": 939,
        "casesPerOneMillion": 387
    },
    {
        "country": "Germany",
        "countryInfo": {"iso2": "DE"},
        "cases": 15320,
        "todayCases": 2993,
        "deaths": 44,
        "todayDeaths": 16,
        "recovered": 115,
        "active": 15161,
        "critical": 2,
        "casesPerOneMillion": 183
    },
    {
        "country": "USA",
        "countryInfo": {"iso2": "US"},
        "cases": 11780,
        "todayCases": 2521,
        "deaths": 176,
        "todayDeaths": 26,
        "recovered": 108,
        "active": 11496,
        "critical": 64,
        "casesPerOneMillion": 36
    },
    {
        "country": "France",
        "countryInfo": {"iso2": "FR"},
        "cases": 10995,
        "todayCases": 1861,
        "deaths": 372,
        "todayDeaths": 108,
        "recovered": 602,
        "active": 10021,
        "critical": 931,
        "casesPerOneMillion": 168
    },
    {
        "country": "S. Korea",
        "countryInfo": {"iso2": "KP"},
        "cases": 8565,
        "todayCases": 152,
        "deaths": 91,
        "todayDeaths": 7,
        "recovered": 1947,
        "active": 6527,
        "critical": 59,
        "casesPerOneMillion": 167
    },
    {
        "country": "Switzerland",
        "countryInfo": {"iso2": "CH"},
        "cases": 4133,
        "todayCases": 1018,
        "deaths": 43,
        "todayDeaths": 10,
        "recovered": 15,
        "active": 4075,
        "critical": 0,
        "casesPerOneMillion": 478
    },
    {
        "country": "UK",
        "countryInfo": {"iso2": "GB"},
        "cases": 3269,
        "todayCases": 643,
        "deaths": 144,
        "todayDeaths": 40,
        "recovered": 65,
        "active": 3060,
        "critical": 20,
        "casesPerOneMillion": 48
    },
    {
        "country": "Netherlands",
        "countryInfo": {"iso2": "NL"},
        "cases": 2460,
        "todayCases": 409,
        "deaths": 76,
        "todayDeaths": 18,
        "recovered": 2,
        "active": 2382,
        "critical": 45,
        "casesPerOneMillion": 144
    },
    {
        "country": "Austria",
        "countryInfo": {"iso2": "AT"},
        "cases": 2179,
        "todayCases": 533,
        "deaths": 6,
        "todayDeaths": 2,
        "recovered": 9,
        "active": 2164,
        "critical": 13,
        "casesPerOneMillion": 242
    },
    {
        "country": "Belgium",
        "countryInfo": {"iso2": "BE"},
        "cases": 1795,
        "todayCases": 309,
        "deaths": 21,
        "todayDeaths": 7,
        "recovered": 165,
        "active": 1609,
        "critical": 130,
        "casesPerOneMillion": 155
    },
    {
        "country": "Norway",
        "countryInfo": {"iso2": "NO"},
        "cases": 1790,
        "todayCases": 199,
        "deaths": 7,
        "todayDeaths": 1,
        "recovered": 1,
        "active": 1782,
        "critical": 27,
        "casesPerOneMillion": 330
    },
    {
        "country": "Sweden",
        "countryInfo": {"iso2": "SE"},
        "cases": 1439,
        "todayCases": 138,
        "deaths": 11,
        "todayDeaths": 1,
        "recovered": 16,
        "active": 1412,
        "critical": 21,
        "casesPerOneMillion": 142
    },
    {
        "country": "Denmark",
        "countryInfo": {"iso2": "DK"},
        "cases": 1151,
        "todayCases": 94,
        "deaths": 6,
        "todayDeaths": 2,
        "recovered": 1,
        "active": 1144,
        "critical": 30,
        "casesPerOneMillion": 199
    },
    {
        "country": "Japan",
        "countryInfo": {"iso2": "JP"},
        "cases": 923,
        "todayCases": 9,
        "deaths": 32,
        "todayDeaths": 3,
        "recovered": 191,
        "active": 700,
        "critical": 46,
        "casesPerOneMillion": 7
    },
    {
        "country": "Malaysia",
        "countryInfo": {"iso2": "MY"},
        "cases": 900,
        "todayCases": 110,
        "deaths": 2,
        "todayDeaths": 0,
        "recovered": 75,
        "active": 823,
        "critical": 15,
        "casesPerOneMillion": 28
    },
    {
        "country": "Canada",
        "countryInfo": {"iso2": "CA"},
        "cases": 801,
        "todayCases": 74,
        "deaths": 10,
        "todayDeaths": 1,
        "recovered": 11,
        "active": 780,
        "critical": 1,
        "casesPerOneMillion": 21
    },
    {
        "country": "Portugal",
        "countryInfo": {"iso2": "PT"},
        "cases": 785,
        "todayCases": 143,
        "deaths": 4,
        "todayDeaths": 2,
        "recovered": 4,
        "active": 777,
        "critical": 20,
        "casesPerOneMillion": 77
    },
    {
        "country": "Australia",
        "countryInfo": {"iso2": "AU"},
        "cases": 709,
        "todayCases": 113,
        "deaths": 6,
        "todayDeaths": 0,
        "recovered": 46,
        "active": 657,
        "critical": 1,
        "casesPerOneMillion": 28
    },
    {
        "country": "Czechia",
        "countryInfo": {"iso2": "CZ"},
        "cases": 694,
        "todayCases": 172,
        "deaths": 0,
        "todayDeaths": 0,
        "recovered": 3,
        "active": 691,
        "critical": 6,
        "casesPerOneMillion": 65
    },
    {
        "country": "Israel",
        "countryInfo": {"iso2": "IL"},
        "cases": 677,
        "todayCases": 244,
        "deaths": 0,
        "todayDeaths": 0,
        "recovered": 14,
        "active": 663,
        "critical": 6,
        "casesPerOneMillion": 78
    },
    {
        "country": "Brazil",
        "countryInfo": {"iso2": "BR"},
        "cases": 621,
        "todayCases": 92,
        "deaths": 7,
        "todayDeaths": 3,
        "recovered": 2,
        "active": 612,
        "critical": 18,
        "casesPerOneMillion": 3
    },
    {
        "country": "Ireland",
        "countryInfo": {"iso2": "IE"},
        "cases": 557,
        "todayCases": 191,
        "deaths": 3,
        "todayDeaths": 1,
        "recovered": 5,
        "active": 549,
        "critical": 6,
        "casesPerOneMillion": 113
    },
    {
        "country": "Greece",
        "countryInfo": {"iso2": "GR"},
        "cases": 464,
        "todayCases": 46,
        "deaths": 6,
        "todayDeaths": 1,
        "recovered": 19,
        "active": 439,
        "critical": 16,
        "casesPerOneMillion": 45
    },
    {
        "country": "Qatar",
        "countryInfo": {"iso2": "QA"},
        "cases": 460,
        "todayCases": 8,
        "deaths": 0,
        "todayDeaths": 0,
        "recovered": 10,
        "active": 450,
        "critical": 6,
        "casesPerOneMillion": 160
    },
    {
        "country": "Pakistan",
        "countryInfo": {"iso2": "PK"},
        "cases": 454,
        "todayCases": 147,
        "deaths": 2,
        "todayDeaths": 0,
        "recovered": 13,
        "active": 439,
        "critical": 0,
        "casesPerOneMillion": 2
    },
    {
        "country": "Finland",
        "countryInfo": {"iso2": "FI"},
        "cases": 400,
        "todayCases": 41,
        "deaths": 0,
        "todayDeaths": 0,
        "recovered": 10,
        "active": 390,
        "critical": 2,
        "casesPerOneMillion": 72
    },
    {
        "country": "Poland",
        "countryInfo": {"iso2": "PL"},
        "cases": 355,
        "todayCases": 68,
        "deaths": 5,
        "todayDeaths": 0,
        "recovered": 13,
        "active": 337,
        "critical": 3,
        "casesPerOneMillion": 9
    },
    {
        "country": "Singapore",
        "countryInfo": {"iso2": "SG"},
        "cases": 345,
        "todayCases": 32,
        "deaths": 0,
        "todayDeaths": 0,
        "recovered": 124,
        "active": 221,
        "critical": 14,
        "casesPerOneMillion": 59
    },
    {
        "country": "Chile",
        "countryInfo": {"iso2": "CL"},
        "cases": 342,
        "todayCases": 104,
        "deaths": 0,
        "todayDeaths": 0,
        "recovered": 0,
        "active": 342,
        "critical": 6,
        "casesPerOneMillion": 18
    },
    {
        "country": "Luxembourg",
        "countryInfo": {"iso2": "LU"},
        "cases": 335,
        "todayCases": 132,
        "deaths": 4,
        "todayDeaths": 2,
        "recovered": 6,
        "active": 325,
        "critical": 1,
        "casesPerOneMillion": 535
    },
    {
        "country": "Iceland",
        "countryInfo": {"iso2": "IS"},
        "cases": 330,
        "todayCases": 80,
        "deaths": 0,
        "todayDeaths": 0,
        "recovered": 5,
        "active": 325,
        "critical": 1,
        "casesPerOneMillion": 967
    },
    {
        "country": "Slovenia",
        "countryInfo": {"iso2": "SI"},
        "cases": 319,
        "todayCases": 33,
        "deaths": 1,
        "todayDeaths": 0,
        "recovered": 0,
        "active": 318,
        "critical": 6,
        "casesPerOneMillion": 153
    },
    {
        "country": "Indonesia",
        "countryInfo": {"iso2": "ID"},
        "cases": 308,
        "todayCases": 81,
        "deaths": 25,
        "todayDeaths": 6,
        "recovered": 15,
        "active": 268,
        "critical": 0,
        "casesPerOneMillion": 1
    },
    {
        "country": "Bahrain",
        "countryInfo": {"iso2": "BH"},
        "cases": 278,
        "todayCases": 22,
        "deaths": 1,
        "todayDeaths": 0,
        "recovered": 110,
        "active": 167,
        "critical": 4,
        "casesPerOneMillion": 163
    },
    {
        "country": "Romania",
        "countryInfo": {"iso2": "RO"},
        "cases": 277,
        "todayCases": 17,
        "deaths": 0,
        "todayDeaths": 0,
        "recovered": 25,
        "active": 252,
        "critical": 5,
        "casesPerOneMillion": 14
    },
    {
        "country": "Saudi Arabia",
        "countryInfo": {"iso2": "SA"},
        "cases": 274,
        "todayCases": 36,
        "deaths": 0,
        "todayDeaths": 0,
        "recovered": 8,
        "active": 266,
        "critical": 0,
        "casesPerOneMillion": 8
    },
    {
        "country": "Thailand",
        "countryInfo": {"iso2": "TH"},
        "cases": 272,
        "todayCases": 60,
        "deaths": 1,
        "todayDeaths": 0,
        "recovered": 42,
        "active": 229,
        "critical": 1,
        "casesPerOneMillion": 4
    },
    {
        "country": "Estonia",
        "countryInfo": {"iso2": "EE"},
        "cases": 267,
        "todayCases": 9,
        "deaths": 0,
        "todayDeaths": 0,
        "recovered": 1,
        "active": 266,
        "critical": 1,
        "casesPerOneMillion": 201
    },
    {
        "country": "Egypt",
        "countryInfo": {"iso2": "EG"},
        "cases": 256,
        "todayCases": 46,
        "deaths": 7,
        "todayDeaths": 1,
        "recovered": 42,
        "active": 207,
        "critical": 0,
        "casesPerOneMillion": 3
    },
    {
        "country": "Peru",
        "countryInfo": {"iso2": "PE"},
        "cases": 234,
        "todayCases": 89,
        "deaths": 0,
        "todayDeaths": 0,
        "recovered": 1,
        "active": 233,
        "critical": 7,
        "casesPerOneMillion": 7
    },
    {
        "country": "Philippines",
        "countryInfo": {"iso2": "PH"},
        "cases": 217,
        "todayCases": 15,
        "deaths": 17,
        "todayDeaths": 0,
        "recovered": 8,
        "active": 192,
        "critical": 1,
        "casesPerOneMillion": 2
    },
    {
        "country": "Hong Kong",
        "countryInfo": {"iso2": "HK"},
        "cases": 208,
        "todayCases": 15,
        "deaths": 4,
        "todayDeaths": 0,
        "recovered": 98,
        "active": 106,
        "critical": 4,
        "casesPerOneMillion": 28
    },
    {
        "country": "Ecuador",
        "countryInfo": {"iso2": "EC"},
        "cases": 199,
        "todayCases": 31,
        "deaths": 3,
        "todayDeaths": 0,
        "recovered": 1,
        "active": 195,
        "critical": 2,
        "casesPerOneMillion": 11
    },
    {
        "country": "Russia",
        "countryInfo": {"iso2": "RU"},
        "cases": 199,
        "todayCases": 52,
        "deaths": 1,
        "todayDeaths": 1,
        "recovered": 8,
        "active": 190,
        "critical": 0,
        "casesPerOneMillion": 1
    },
    {
        "country": "India",
        "countryInfo": {"iso2": "IN"},
        "cases": 194,
        "todayCases": 25,
        "deaths": 4,
        "todayDeaths": 1,
        "recovered": 20,
        "active": 170,
        "critical": 0,
        "casesPerOneMillion": 0
    },
    {
        "country": "Iraq",
        "countryInfo": {"iso2": "IQ"},
        "cases": 192,
        "todayCases": 28,
        "deaths": 13,
        "todayDeaths": 1,
        "recovered": 49,
        "active": 130,
        "critical": 0,
        "casesPerOneMillion": 5
    },
    {
        "country": "Turkey",
        "countryInfo": {"iso2": "TR"},
        "cases": 192,
        "todayCases": 1,
        "deaths": 4,
        "todayDeaths": 2,
        "recovered": 0,
        "active": 188,
        "critical": 0,
        "casesPerOneMillion": 2
    },
    {
        "country": "Lebanon",
        "countryInfo": {"iso2": "LB"},
        "cases": 157,
        "todayCases": 24,
        "deaths": 4,
        "todayDeaths": 0,
        "recovered": 4,
        "active": 149,
        "critical": 3,
        "casesPerOneMillion": 23
    },
    {
        "country": "South Africa",
        "countryInfo": {"iso2": "ZA"},
        "cases": 150,
        "todayCases": 34,
        "deaths": 0,
        "todayDeaths": 0,
        "recovered": 0,
        "active": 150,
        "critical": 0,
        "casesPerOneMillion": 3
    },
    {
        "country": "Kuwait",
        "countryInfo": {"iso2": "KW"},
        "cases": 148,
        "todayCases": 6,
        "deaths": 0,
        "todayDeaths": 0,
        "recovered": 18,
        "active": 130,
        "critical": 5,
        "casesPerOneMillion": 35
    },
    {
        "country": "San Marino",
        "countryInfo": {"iso2": "SM"},
        "cases": 140,
        "todayCases": 0,
        "deaths": 14,
        "todayDeaths": 0,
        "recovered": 4,
        "active": 122,
        "critical": 11,
        "casesPerOneMillion": 4126
    },
    {
        "country": "UAE",
        "countryInfo": {"iso2": "AE"},
        "cases": 140,
        "todayCases": 27,
        "deaths": 0,
        "todayDeaths": 0,
        "recovered": 31,
        "active": 109,
        "critical": 2,
        "casesPerOneMillion": 14
    },
    {
        "country": "Slovakia",
        "countryInfo": {"iso2": "SK"},
        "cases": 124,
        "todayCases": 19,
        "deaths": 0,
        "todayDeaths": 0,
        "recovered": 0,
        "active": 124,
        "critical": 2,
        "casesPerOneMillion": 23
    },
    {
        "country": "Armenia",
        "countryInfo": {"iso2": "AM"},
        "cases": 122,
        "todayCases": 12,
        "deaths": 0,
        "todayDeaths": 0,
        "recovered": 1,
        "active": 121,
        "critical": 2,
        "casesPerOneMillion": 41
    },
    {
        "country": "Mexico",
        "countryInfo": {"iso2": "MX"},
        "cases": 118,
        "todayCases": 25,
        "deaths": 1,
        "todayDeaths": 1,
        "recovered": 4,
        "active": 113,
        "critical": 1,
        "casesPerOneMillion": 0
    },
    {
        "country": "Croatia",
        "countryInfo": {"iso2": "HR"},
        "cases": 110,
        "todayCases": 21,
        "deaths": 1,
        "todayDeaths": 1,
        "recovered": 5,
        "active": 104,
        "critical": 0,
        "casesPerOneMillion": 27
    },
    {
        "country": "Panama",
        "countryInfo": {"iso2": "PA"},
        "cases": 109,
        "todayCases": 0,
        "deaths": 1,
        "todayDeaths": 0,
        "recovered": 0,
        "active": 108,
        "critical": 7,
        "casesPerOneMillion": 25
    },
    {
        "country": "Taiwan",
        "countryInfo": {"iso2": "TW"},
        "cases": 108,
        "todayCases": 8,
        "deaths": 1,
        "todayDeaths": 0,
        "recovered": 26,
        "active": 81,
        "critical": 0,
        "casesPerOneMillion": 5
    },
    {
        "country": "Colombia",
        "countryInfo": {"iso2": "CO"},
        "cases": 108,
        "todayCases": 15,
        "deaths": 0,
        "todayDeaths": 0,
        "recovered": 1,
        "active": 107,
        "critical": 0,
        "casesPerOneMillion": 2
    },
    {
        "country": "Bulgaria",
        "countryInfo": {"iso2": "BG"},
        "cases": 107,
        "todayCases": 15,
        "deaths": 3,
        "todayDeaths": 1,
        "recovered": 0,
        "active": 104,
        "critical": 0,
        "casesPerOneMillion": 15
    },
    {
        "country": "Serbia",
        "countryInfo": {"iso2": "RS"},
        "cases": 103,
        "todayCases": 14,
        "deaths": 0,
        "todayDeaths": 0,
        "recovered": 1,
        "active": 102,
        "critical": 4,
        "casesPerOneMillion": 12
    },
    {
        "country": "Argentina",
        "countryInfo": {"iso2": "AR"},
        "cases": 97,
        "todayCases": 0,
        "deaths": 3,
        "todayDeaths": 1,
        "recovered": 3,
        "active": 91,
        "critical": 0,
        "casesPerOneMillion": 2
    },
    {
        "country": "Algeria",
        "countryInfo": {"iso2": "DZ"},
        "cases": 90,
        "todayCases": 15,
        "deaths": 9,
        "todayDeaths": 2,
        "recovered": 32,
        "active": 49,
        "critical": 0,
        "casesPerOneMillion": 2
    },
    {
        "country": "Costa Rica",
        "countryInfo": {"iso2": "CR"},
        "cases": 87,
        "todayCases": 18,
        "deaths": 1,
        "todayDeaths": 0,
        "recovered": 0,
        "active": 86,
        "critical": 2,
        "casesPerOneMillion": 17
    },
    {
        "country": "Latvia",
        "countryInfo": {"iso2": "LV"},
        "cases": 86,
        "todayCases": 15,
        "deaths": 0,
        "todayDeaths": 0,
        "recovered": 1,
        "active": 85,
        "critical": 0,
        "casesPerOneMillion": 46
    },
    {
        "country": "Vietnam",
        "countryInfo": {"iso2": "VN"},
        "cases": 85,
        "todayCases": 9,
        "deaths": 0,
        "todayDeaths": 0,
        "recovered": 16,
        "active": 69,
        "critical": 0,
        "casesPerOneMillion": 0
    },
    {
        "country": "Uruguay",
        "countryInfo": {"iso2": "UY"},
        "cases": 79,
        "todayCases": 0,
        "deaths": 0,
        "todayDeaths": 0,
        "recovered": 0,
        "active": 79,
        "critical": 0,
        "casesPerOneMillion": 23
    },
    {
        "country": "Andorra",
        "countryInfo": {"iso2": "AD"},
        "cases": 74,
        "todayCases": 21,
        "deaths": 0,
        "todayDeaths": 0,
        "recovered": 1,
        "active": 73,
        "critical": 0,
        "casesPerOneMillion": 958
    },
    {
        "country": "Hungary",
        "countryInfo": {"iso2": "HU"},
        "cases": 73,
        "todayCases": 15,
        "deaths": 1,
        "todayDeaths": 0,
        "recovered": 2,
        "active": 70,
        "critical": 4,
        "casesPerOneMillion": 8
    },
    {
        "country": "Brunei",
        "countryInfo": {"iso2": "BN"},
        "cases": 73,
        "todayCases": 5,
        "deaths": 0,
        "todayDeaths": 0,
        "recovered": 0,
        "active": 73,
        "critical": 2,
        "casesPerOneMillion": 167
    },
    {
        "country": "Faeroe Islands",
        "countryInfo": {"iso2": "FO"},
        "cases": 72,
        "todayCases": 14,
        "deaths": 0,
        "todayDeaths": 0,
        "recovered": 1,
        "active": 71,
        "critical": 0,
        "casesPerOneMillion": 1474
    },
    {
        "country": "Jordan",
        "countryInfo": {"iso2": "JO"},
        "cases": 69,
        "todayCases": 13,
        "deaths": 0,
        "todayDeaths": 0,
        "recovered": 1,
        "active": 68,
        "critical": 0,
        "casesPerOneMillion": 7
    },
    {
        "country": "Cyprus",
        "countryInfo": {"iso2": "CY"},
        "cases": 67,
        "todayCases": 9,
        "deaths": 0,
        "todayDeaths": 0,
        "recovered": 0,
        "active": 67,
        "critical": 1,
        "casesPerOneMillion": 55
    },
    {
        "country": "Albania",
        "countryInfo": {"iso2": "AL"},
        "cases": 64,
        "todayCases": 5,
        "deaths": 2,
        "todayDeaths": 0,
        "recovered": 0,
        "active": 62,
        "critical": 2,
        "casesPerOneMillion": 22
    },
    {
        "country": "Bosnia and Herzegovina",
        "countryInfo": {"iso2": "BA"},
        "cases": 64,
        "todayCases": 25,
        "deaths": 0,
        "todayDeaths": 0,
        "recovered": 2,
        "active": 62,
        "critical": 0,
        "casesPerOneMillion": 20
    },
    {
        "country": "Morocco",
        "countryInfo": {"iso2": "MA"},
        "cases": 63,
        "todayCases": 9,
        "deaths": 2,
        "todayDeaths": 0,
        "recovered": 2,
        "active": 59,
        "critical": 1,
        "casesPerOneMillion": 2
    },
    {
        "country": "Sri Lanka",
        "countryInfo": {"iso2": "LK"},
        "cases": 60,
        "todayCases": 9,
        "deaths": 0,
        "todayDeaths": 0,
        "recovered": 3,
        "active": 57,
        "critical": 0,
        "casesPerOneMillion": 3
    },
    {
        "country": "Malta",
        "countryInfo": {"iso2": "MT"},
        "cases": 53,
        "todayCases": 5,
        "deaths": 0,
        "todayDeaths": 0,
        "recovered": 2,
        "active": 51,
        "critical": 0,
        "casesPerOneMillion": 120
    },
    {
        "country": "Belarus",
        "countryInfo": {"iso2": "BY"},
        "cases": 51,
        "todayCases": 0,
        "deaths": 0,
        "todayDeaths": 0,
        "recovered": 5,
        "active": 46,
        "critical": 0,
        "casesPerOneMillion": 5
    },
    {
        "country": "North Macedonia",
        "countryInfo": {"iso2": "MK"},
        "cases": 50,
        "todayCases": 7,
        "deaths": 0,
        "todayDeaths": 0,
        "recovered": 1,
        "active": 49,
        "critical": 1,
        "casesPerOneMillion": 24
    },
    {
        "country": "Moldova",
        "countryInfo": {"iso2": "MD"},
        "cases": 49,
        "todayCases": 13,
        "deaths": 1,
        "todayDeaths": 0,
        "recovered": 1,
        "active": 47,
        "critical": 3,
        "casesPerOneMillion": 12
    },
    {
        "country": "Oman",
        "countryInfo": {"iso2": "OM"},
        "cases": 48,
        "todayCases": 9,
        "deaths": 0,
        "todayDeaths": 0,
        "recovered": 13,
        "active": 35,
        "critical": 0,
        "casesPerOneMillion": 9
    },
    {
        "country": "Palestine",
        "countryInfo": {"iso2": "PS"},
        "cases": 47,
        "todayCases": 3,
        "deaths": 0,
        "todayDeaths": 0,
        "recovered": 0,
        "active": 47,
        "critical": 0,
        "casesPerOneMillion": 9
    },
    {
        "country": "Kazakhstan",
        "countryInfo": {"iso2": "KZ"},
        "cases": 44,
        "todayCases": 8,
        "deaths": 3,
        "todayDeaths": 3,
        "recovered": 0,
        "active": 41,
        "critical": 0,
        "casesPerOneMillion": 2
    },
    {
        "country": "Azerbaijan",
        "countryInfo": {"iso2": "AZ"},
        "cases": 44,
        "todayCases": 10,
        "deaths": 1,
        "todayDeaths": 0,
        "recovered": 7,
        "active": 36,
        "critical": 0,
        "casesPerOneMillion": 4
    },
    {
        "country": "Venezuela",
        "countryInfo": {"iso2": "VE"},
        "cases": 42,
        "todayCases": 6,
        "deaths": 0,
        "todayDeaths": 0,
        "recovered": 0,
        "active": 42,
        "critical": 0,
        "casesPerOneMillion": 1
    },
    {
        "country": "Lithuania",
        "countryInfo": {"iso2": "LT"},
        "cases": 41,
        "todayCases": 7,
        "deaths": 0,
        "todayDeaths": 0,
        "recovered": 1,
        "active": 40,
        "critical": 1,
        "casesPerOneMillion": 15
    },
    {
        "country": "Georgia",
        "countryInfo": {"iso2": "GE"},
        "cases": 40,
        "todayCases": 2,
        "deaths": 0,
        "todayDeaths": 0,
        "recovered": 1,
        "active": 39,
        "critical": 1,
        "casesPerOneMillion": 10
    },
    {
        "country": "Tunisia",
        "countryInfo": {"iso2": "TN"},
        "cases": 39,
        "todayCases": 10,
        "deaths": 1,
        "todayDeaths": 1,
        "recovered": 1,
        "active": 37,
        "critical": 2,
        "casesPerOneMillion": 3
    },
    {
        "country": "Cambodia",
        "countryInfo": {"iso2": "KH"},
        "cases": 37,
        "todayCases": 0,
        "deaths": 0,
        "todayDeaths": 0,
        "recovered": 1,
        "active": 36,
        "critical": 0,
        "casesPerOneMillion": 2
    },
    {
        "country": "Senegal",
        "countryInfo": {"iso2": "SN"},
        "cases": 36,
        "todayCases": 0,
        "deaths": 0,
        "todayDeaths": 0,
        "recovered": 2,
        "active": 34,
        "critical": 0,
        "casesPerOneMillion": 2
    },
    {
        "country": "Dominican Republic",
        "countryInfo": {"iso2": "DO"},
        "cases": 34,
        "todayCases": 0,
        "deaths": 2,
        "todayDeaths": 0,
        "recovered": 0,
        "active": 32,
        "critical": 0,
        "casesPerOneMillion": 3
    },
    {
        "country": "Burkina Faso",
        "countryInfo": {"iso2": "BF"},
        "cases": 33,
        "todayCases": 6,
        "deaths": 1,
        "todayDeaths": 0,
        "recovered": 0,
        "active": 32,
        "critical": 0,
        "casesPerOneMillion": 2
    },
    {
        "country": "Guadeloupe",
        "countryInfo": {"iso2": "GP"},
        "cases": 33,
        "todayCases": 0,
        "deaths": 0,
        "todayDeaths": 0,
        "recovered": 0,
        "active": 33,
        "critical": 0,
        "casesPerOneMillion": 82
    },
    {
        "country": "New Zealand",
        "countryInfo": {"iso2": "NZ"},
        "cases": 28,
        "todayCases": 8,
        "deaths": 0,
        "todayDeaths": 0,
        "recovered": 0,
        "active": 28,
        "critical": 0,
        "casesPerOneMillion": 6
    },
    {
        "country": "Liechtenstein",
        "countryInfo": {"iso2": "LI"},
        "cases": 28,
        "todayCases": 0,
        "deaths": 0,
        "todayDeaths": 0,
        "recovered": 0,
        "active": 28,
        "critical": 0,
        "casesPerOneMillion": 734
    },
    {
        "country": "Réunion",
        "countryInfo": {"iso2": "RE"},
        "cases": 28,
        "todayCases": 14,
        "deaths": 0,
        "todayDeaths": 0,
        "recovered": 0,
        "active": 28,
        "critical": 0,
        "casesPerOneMillion": 31
    },
    {
        "country": "Martinique",
        "countryInfo": {"iso2": "MQ"},
        "cases": 23,
        "todayCases": 0,
        "deaths": 1,
        "todayDeaths": 0,
        "recovered": 0,
        "active": 22,
        "critical": 0,
        "casesPerOneMillion": 61
    },
    {
        "country": "Uzbekistan",
        "countryInfo": {"iso2": "UZ"},
        "cases": 23,
        "todayCases": 5,
        "deaths": 0,
        "todayDeaths": 0,
        "recovered": 0,
        "active": 23,
        "critical": 0,
        "casesPerOneMillion": 0
    },
    {
        "country": "Afghanistan",
        "countryInfo": {"iso2": "AF"},
        "cases": 22,
        "todayCases": 0,
        "deaths": 0,
        "todayDeaths": 0,
        "recovered": 1,
        "active": 21,
        "critical": 0,
        "casesPerOneMillion": 0
    },
    {
        "country": "Ukraine",
        "countryInfo": {"iso2": "UA"},
        "cases": 21,
        "todayCases": 5,
        "deaths": 3,
        "todayDeaths": 1,
        "recovered": 0,
        "active": 18,
        "critical": 0,
        "casesPerOneMillion": 0
    },
    {
        "country": "Bangladesh",
        "countryInfo": {"iso2": "BD"},
        "cases": 18,
        "todayCases": 4,
        "deaths": 1,
        "todayDeaths": 0,
        "recovered": 3,
        "active": 14,
        "critical": 0,
        "casesPerOneMillion": 0
    },
    {
        "country": "Macao",
        "countryInfo": {"iso2": "MO"},
        "cases": 17,
        "todayCases": 0,
        "deaths": 0,
        "todayDeaths": 0,
        "recovered": 10,
        "active": 7,
        "critical": 0,
        "casesPerOneMillion": 26
    },
    {
        "country": "Jamaica",
        "countryInfo": {"iso2": "JM"},
        "cases": 15,
        "todayCases": 0,
        "deaths": 1,
        "todayDeaths": 0,
        "recovered": 2,
        "active": 12,
        "critical": 0,
        "casesPerOneMillion": 5
    },
    {
        "country": "Bolivia",
        "countryInfo": {"iso2": "BO"},
        "cases": 15,
        "todayCases": 3,
        "deaths": 0,
        "todayDeaths": 0,
        "recovered": 0,
        "active": 15,
        "critical": 0,
        "casesPerOneMillion": 1
    },
    {
        "country": "French Guiana",
        "countryInfo": {"iso2": "GF"},
        "cases": 15,
        "todayCases": 0,
        "deaths": 0,
        "todayDeaths": 0,
        "recovered": 0,
        "active": 15,
        "critical": 0,
        "casesPerOneMillion": 50
    },
    {
        "country": "Cameroon",
        "countryInfo": {"iso2": "CM"},
        "cases": 13,
        "todayCases": 0,
        "deaths": 0,
        "todayDeaths": 0,
        "recovered": 0,
        "active": 13,
        "critical": 0,
        "casesPerOneMillion": 0
    },
    {
        "country": "Maldives",
        "countryInfo": {"iso2": "MV"},
        "cases": 13,
        "todayCases": 0,
        "deaths": 0,
        "todayDeaths": 0,
        "recovered": 0,
        "active": 13,
        "critical": 0,
        "casesPerOneMillion": 24
    },
    {
        "country": "Nigeria",
        "countryInfo": {"iso2": "NG"},
        "cases": 12,
        "todayCases": 4,
        "deaths": 0,
        "todayDeaths": 0,
        "recovered": 1,
        "active": 11,
        "critical": 0,
        "casesPerOneMillion": 0
    },
    {
        "country": "Guam",
        "countryInfo": {"iso2": "GU"},
        "cases": 12,
        "todayCases": 4,
        "deaths": 0,
        "todayDeaths": 0,
        "recovered": 0,
        "active": 12,
        "critical": 0,
        "casesPerOneMillion": 71
    },
    {
        "country": "Honduras",
        "countryInfo": {"iso2": "HN"},
        "cases": 12,
        "todayCases": 3,
        "deaths": 0,
        "todayDeaths": 0,
        "recovered": 0,
        "active": 12,
        "critical": 0,
        "casesPerOneMillion": 1
    },
    {
        "country": "Cuba",
        "countryInfo": {"iso2": "CU"},
        "cases": 11,
        "todayCases": 1,
        "deaths": 1,
        "todayDeaths": 0,
        "recovered": 0,
        "active": 10,
        "critical": 0,
        "casesPerOneMillion": 1
    },
    {
        "country": "Ghana",
        "countryInfo": {"iso2": "GH"},
        "cases": 11,
        "todayCases": 4,
        "deaths": 0,
        "todayDeaths": 0,
        "recovered": 0,
        "active": 11,
        "critical": 0,
        "casesPerOneMillion": 0
    },
    {
        "country": "Paraguay",
        "countryInfo": {"iso2": "PY"},
        "cases": 11,
        "todayCases": 0,
        "deaths": 0,
        "todayDeaths": 0,
        "recovered": 0,
        "active": 11,
        "critical": 1,
        "casesPerOneMillion": 2
    },
    {
        "country": "Rwanda",
        "countryInfo": {"iso2": "RW"},
        "cases": 11,
        "todayCases": 0,
        "deaths": 0,
        "todayDeaths": 0,
        "recovered": 0,
        "active": 11,
        "critical": 0,
        "casesPerOneMillion": 0
    },
    {
        "country": "Monaco",
        "countryInfo": {"iso2": "MC"},
        "cases": 10,
        "todayCases": 1,
        "deaths": 0,
        "todayDeaths": 0,
        "recovered": 0,
        "active": 10,
        "critical": 0,
        "casesPerOneMillion": 255
    },
    {
        "country": "Gibraltar",
        "countryInfo": {"iso2": "GI"},
        "cases": 10,
        "todayCases": 2,
        "deaths": 0,
        "todayDeaths": 0,
        "recovered": 2,
        "active": 8,
        "critical": 0,
        "casesPerOneMillion": 297
    },
    {
        "country": "Montenegro",
        "countryInfo": {"iso2": "ME"},
        "cases": 10,
        "todayCases": 2,
        "deaths": 0,
        "todayDeaths": 0,
        "recovered": 0,
        "active": 10,
        "critical": 0,
        "casesPerOneMillion": 16
    },
    {
        "country": "Guatemala",
        "countryInfo": {"iso2": "GT"},
        "cases": 9,
        "todayCases": 1,
        "deaths": 1,
        "todayDeaths": 0,
        "recovered": 0,
        "active": 8,
        "critical": 0,
        "casesPerOneMillion": 0
    },
    {
        "country": "Trinidad and Tobago",
        "countryInfo": {"iso2": "TT"},
        "cases": 9,
        "todayCases": 2,
        "deaths": 0,
        "todayDeaths": 0,
        "recovered": 0,
        "active": 9,
        "critical": 0,
        "casesPerOneMillion": 6
    },
    {
        "country": "Ethiopia",
        "countryInfo": {"iso2": "ET"},
        "cases": 7,
        "todayCases": 1,
        "deaths": 0,
        "todayDeaths": 0,
        "recovered": 0,
        "active": 7,
        "critical": 0,
        "casesPerOneMillion": 0
    },
    {
        "country": "Kenya",
        "countryInfo": {"iso2": "KE"},
        "cases": 7,
        "todayCases": 0,
        "deaths": 0,
        "todayDeaths": 0,
        "recovered": 0,
        "active": 7,
        "critical": 0,
        "casesPerOneMillion": 0
    },
    {
        "country": "Mauritius",
        "countryInfo": {"iso2": "MU"},
        "cases": 7,
        "todayCases": 4,
        "deaths": 0,
        "todayDeaths": 0,
        "recovered": 0,
        "active": 7,
        "critical": 0,
        "casesPerOneMillion": 6
    },
    {
        "country": "Equatorial Guinea",
        "countryInfo": {"iso2": "GQ"},
        "cases": 6,
        "todayCases": 2,
        "deaths": 0,
        "todayDeaths": 0,
        "recovered": 0,
        "active": 6,
        "critical": 0,
        "casesPerOneMillion": 4
    },
    {
        "country": "French Polynesia",
        "countryInfo": {"iso2": "PF"},
        "cases": 6,
        "todayCases": 1,
        "deaths": 0,
        "todayDeaths": 0,
        "recovered": 0,
        "active": 6,
        "critical": 0,
        "casesPerOneMillion": 21
    },
    {
        "country": "Mongolia",
        "countryInfo": {"iso2": "MN"},
        "cases": 6,
        "todayCases": 0,
        "deaths": 0,
        "todayDeaths": 0,
        "recovered": 0,
        "active": 6,
        "critical": 0,
        "casesPerOneMillion": 2
    },
    {
        "country": "Puerto Rico",
        "countryInfo": {"iso2": "PR"},
        "cases": 6,
        "todayCases": 0,
        "deaths": 0,
        "todayDeaths": 0,
        "recovered": 0,
        "active": 6,
        "critical": 0,
        "casesPerOneMillion": 2
    },
    {
        "country": "Seychelles",
        "countryInfo": {"iso2": "SC"},
        "cases": 6,
        "todayCases": 0,
        "deaths": 0,
        "todayDeaths": 0,
        "recovered": 0,
        "active": 6,
        "critical": 0,
        "casesPerOneMillion": 61
    },
    {
        "country": "Tanzania",
        "countryInfo": {"iso2": "TZ"},
        "cases": 6,
        "todayCases": 3,
        "deaths": 0,
        "todayDeaths": 0,
        "recovered": 0,
        "active": 6,
        "critical": 0,
        "casesPerOneMillion": 0
    },
    {
        "country": "Guyana",
        "countryInfo": {"iso2": "GY"},
        "cases": 5,
        "todayCases": 1,
        "deaths": 1,
        "todayDeaths": 0,
        "recovered": 0,
        "active": 4,
        "critical": 0,
        "casesPerOneMillion": 6
    },
    {
        "country": "Aruba",
        "countryInfo": {"iso2": "AW"},
        "cases": 5,
        "todayCases": 1,
        "deaths": 0,
        "todayDeaths": 0,
        "recovered": 1,
        "active": 4,
        "critical": 0,
        "casesPerOneMillion": 47
    },
    {
        "country": "Barbados",
        "countryInfo": {"iso2": "BB"},
        "cases": 5,
        "todayCases": 3,
        "deaths": 0,
        "todayDeaths": 0,
        "recovered": 0,
        "active": 5,
        "critical": 0,
        "casesPerOneMillion": 17
    },
    {
        "country": "Cayman Islands",
        "countryInfo": {"iso2": "KY"},
        "cases": 3,
        "todayCases": 2,
        "deaths": 1,
        "todayDeaths": 0,
        "recovered": 0,
        "active": 2,
        "critical": 0,
        "casesPerOneMillion": 46
    },
    {
        "country": "Curaçao",
        "countryInfo": {"iso2": "CW"},
        "cases": 3,
        "todayCases": 0,
        "deaths": 1,
        "todayDeaths": 1,
        "recovered": 0,
        "active": 2,
        "critical": 0,
        "casesPerOneMillion": 18
    },
    {
        "country": "Bahamas",
        "countryInfo": {"iso2": "BS"},
        "cases": 3,
        "todayCases": 2,
        "deaths": 0,
        "todayDeaths": 0,
        "recovered": 0,
        "active": 3,
        "critical": 0,
        "casesPerOneMillion": 8
    },
    {
        "country": "Congo",
        "countryInfo": {"iso2": "CG"},
        "cases": 3,
        "todayCases": 2,
        "deaths": 0,
        "todayDeaths": 0,
        "recovered": 0,
        "active": 3,
        "critical": 0,
        "casesPerOneMillion": 0
    },
    {
        "country": "Gabon",
        "countryInfo": {"iso2": "GA"},
        "cases": 3,
        "todayCases": 0,
        "deaths": 0,
        "todayDeaths": 0,
        "recovered": 0,
        "active": 3,
        "critical": 0,
        "casesPerOneMillion": 1
    },
    {
        "country": "Kyrgyzstan",
        "countryInfo": {"iso2": "KG"},
        "cases": 3,
        "todayCases": 0,
        "deaths": 0,
        "todayDeaths": 0,
        "recovered": 0,
        "active": 3,
        "critical": 0,
        "casesPerOneMillion": 0
    },
    {
        "country": "Mayotte",
        "countryInfo": {"iso2": "YT"},
        "cases": 3,
        "todayCases": 0,
        "deaths": 0,
        "todayDeaths": 0,
        "recovered": 0,
        "active": 3,
        "critical": 0,
        "casesPerOneMillion": 11
    },
    {
        "country": "Namibia",
        "countryInfo": {"iso2": "NA"},
        "cases": 3,
        "todayCases": 1,
        "deaths": 0,
        "todayDeaths": 0,
        "recovered": 0,
        "active": 3,
        "critical": 0,
        "casesPerOneMillion": 1
    },
    {
        "country": "St. Barth",
        "countryInfo": {"iso2": "BL"},
        "cases": 3,
        "todayCases": 0,
        "deaths": 0,
        "todayDeaths": 0,
        "recovered": 0,
        "active": 3,
        "critical": 0,
        "casesPerOneMillion": 304
    },
    {
        "country": "Saint Martin",
        "countryInfo": {"iso2": "MF"},
        "cases": 3,
        "todayCases": 0,
        "deaths": 0,
        "todayDeaths": 0,
        "recovered": 0,
        "active": 3,
        "critical": 0,
        "casesPerOneMillion": 78
    },
    {
        "country": "U.S. Virgin Islands",
        "countryInfo": {"iso2": "VI"},
        "cases": 3,
        "todayCases": 1,
        "deaths": 0,
        "todayDeaths": 0,
        "recovered": 0,
        "active": 3,
        "critical": 0,
        "casesPerOneMillion": 29
    },
    {
        "country": "Sudan",
        "countryInfo": {"iso2": "SD"},
        "cases": 2,
        "todayCases": 0,
        "deaths": 1,
        "todayDeaths": 0,
        "recovered": 0,
        "active": 1,
        "critical": 0,
        "casesPerOneMillion": 0
    },
    {
        "country": "Benin",
        "countryInfo": {"iso2": "BJ"},
        "cases": 2,
        "todayCases": 0,
        "deaths": 0,
        "todayDeaths": 0,
        "recovered": 0,
        "active": 2,
        "critical": 0,
        "casesPerOneMillion": 0
    },
    {
        "country": "Bermuda",
        "countryInfo": {"iso2": "BM"},
        "cases": 2,
        "todayCases": 0,
        "deaths": 0,
        "todayDeaths": 0,
        "recovered": 0,
        "active": 2,
        "critical": 0,
        "casesPerOneMillion": 32
    },
    {
        "country": "Greenland",
        "countryInfo": {"iso2": "GL"},
        "cases": 2,
        "todayCases": 0,
        "deaths": 0,
        "todayDeaths": 0,
        "recovered": 0,
        "active": 2,
        "critical": 0,
        "casesPerOneMillion": 35
    },
    {
        "country": "Liberia",
        "countryInfo": {"iso2": "LR"},
        "cases": 2,
        "todayCases": 0,
        "deaths": 0,
        "todayDeaths": 0,
        "recovered": 0,
        "active": 2,
        "critical": 0,
        "casesPerOneMillion": 0
    },
    {
        "country": "Mauritania",
        "countryInfo": {"iso2": "MR"},
        "cases": 2,
        "todayCases": 0,
        "deaths": 0,
        "todayDeaths": 0,
        "recovered": 0,
        "active": 2,
        "critical": 0,
        "casesPerOneMillion": 0
    },
    {
        "country": "New Caledonia",
        "countryInfo": {"iso2": "NC"},
        "cases": 2,
        "todayCases": 0,
        "deaths": 0,
        "todayDeaths": 0,
        "recovered": 0,
        "active": 2,
        "critical": 0,
        "casesPerOneMillion": 7
    },
    {
        "country": "Saint Lucia",
        "countryInfo": {"iso2": "LC"},
        "cases": 2,
        "todayCases": 0,
        "deaths": 0,
        "todayDeaths": 0,
        "recovered": 0,
        "active": 2,
        "critical": 0,
        "casesPerOneMillion": 11
    },
    {
        "country": "Zambia",
        "countryInfo": {"iso2": "ZM"},
        "cases": 2,
        "todayCases": 0,
        "deaths": 0,
        "todayDeaths": 0,
        "recovered": 0,
        "active": 2,
        "critical": 0,
        "casesPerOneMillion": 0
    },
    {
        "country": "Nepal",
        "countryInfo": {"iso2": "NP"},
        "cases": 1,
        "todayCases": 0,
        "deaths": 0,
        "todayDeaths": 0,
        "recovered": 1,
        "active": 0,
        "critical": 0,
        "casesPerOneMillion": 0
    },
    {
        "country": "Antigua and Barbuda",
        "countryInfo": {"iso2": "AG"},
        "cases": 1,
        "todayCases": 0,
        "deaths": 0,
        "todayDeaths": 0,
        "recovered": 0,
        "active": 1,
        "critical": 0,
        "casesPerOneMillion": 10
    },
    {
        "country": "Bhutan",
        "countryInfo": {"iso2": "BT"},
        "cases": 1,
        "todayCases": 0,
        "deaths": 0,
        "todayDeaths": 0,
        "recovered": 0,
        "active": 1,
        "critical": 0,
        "casesPerOneMillion": 1
    },
    {
        "country": "CAR",
        "countryInfo": {"iso2": "CF"},
        "cases": 1,
        "todayCases": 0,
        "deaths": 0,
        "todayDeaths": 0,
        "recovered": 0,
        "active": 1,
        "critical": 0,
        "casesPerOneMillion": 0
    },
    {
        "country": "Chad",
        "countryInfo": {"iso2": "TD"},
        "cases": 1,
        "todayCases": 1,
        "deaths": 0,
        "todayDeaths": 0,
        "recovered": 0,
        "active": 1,
        "critical": 0,
        "casesPerOneMillion": 0
    },
    {
        "country": "Djibouti",
        "countryInfo": {"iso2": "DJ"},
        "cases": 1,
        "todayCases": 0,
        "deaths": 0,
        "todayDeaths": 0,
        "recovered": 0,
        "active": 1,
        "critical": 0,
        "casesPerOneMillion": 1
    },
    {
        "country": "El Salvador",
        "countryInfo": {"iso2": "SV"},
        "cases": 1,
        "todayCases": 1,
        "deaths": 0,
        "todayDeaths": 0,
        "recovered": 0,
        "active": 1,
        "critical": 0,
        "casesPerOneMillion": 0
    },
    {
        "country": "Fiji",
        "countryInfo": {"iso2": "FJ"},
        "cases": 1,
        "todayCases": 1,
        "deaths": 0,
        "todayDeaths": 0,
        "recovered": 0,
        "active": 1,
        "critical": 0,
        "casesPerOneMillion": 1
    },
    {
        "country": "Gambia",
        "countryInfo": {"iso2": "GM"},
        "cases": 1,
        "todayCases": 0,
        "deaths": 0,
        "todayDeaths": 0,
        "recovered": 0,
        "active": 1,
        "critical": 0,
        "casesPerOneMillion": 0
    },
    {
        "country": "Guinea",
        "countryInfo": {"iso2": "GN"},
        "cases": 1,
        "todayCases": 0,
        "deaths": 0,
        "todayDeaths": 0,
        "recovered": 0,
        "active": 1,
        "critical": 0,
        "casesPerOneMillion": 0
    },
    {
        "country": "Montserrat",
        "countryInfo": {"iso2": "MS"},
        "cases": 1,
        "todayCases": 0,
        "deaths": 0,
        "todayDeaths": 0,
        "recovered": 0,
        "active": 1,
        "critical": 0,
        "casesPerOneMillion": 200
    },
    {
        "country": "Nicaragua",
        "countryInfo": {"iso2": "NI"},
        "cases": 1,
        "todayCases": 1,
        "deaths": 0,
        "todayDeaths": 0,
        "recovered": 0,
        "active": 1,
        "critical": 0,
        "casesPerOneMillion": 0
    },
    {
        "country": "Niger",
        "countryInfo": {"iso2": "NE"},
        "cases": 1,
        "todayCases": 1,
        "deaths": 0,
        "todayDeaths": 0,
        "recovered": 0,
        "active": 1,
        "critical": 0,
        "casesPerOneMillion": 0
    },
    {
        "country": "St. Vincent Grenadines",
        "countryInfo": {"iso2": "CV"},
        "cases": 1,
        "todayCases": 0,
        "deaths": 0,
        "todayDeaths": 0,
        "recovered": 0,
        "active": 1,
        "critical": 0,
        "casesPerOneMillion": 9
    },
    {
        "country": "Sint Maarten",
        "countryInfo": {"iso2": "SX"},
        "cases": 1,
        "todayCases": 0,
        "deaths": 0,
        "todayDeaths": 0,
        "recovered": 0,
        "active": 1,
        "critical": 0,
        "casesPerOneMillion": 23
    },
    {
        "country": "Somalia",
        "countryInfo": {"iso2": "SO"},
        "cases": 1,
        "todayCases": 0,
        "deaths": 0,
        "todayDeaths": 0,
        "recovered": 0,
        "active": 1,
        "critical": 0,
        "casesPerOneMillion": 0
    },
    {
        "country": "Suriname",
        "countryInfo": {"iso2": "SR"},
        "cases": 1,
        "todayCases": 0,
        "deaths": 0,
        "todayDeaths": 0,
        "recovered": 0,
        "active": 1,
        "critical": 0,
        "casesPerOneMillion": 2
    },
    {
        "country": "Eswatini",
        "countryInfo": {"iso2": "SZ"},
        "cases": 1,
        "todayCases": 0,
        "deaths": 0,
        "todayDeaths": 0,
        "recovered": 0,
        "active": 1,
        "critical": 0,
        "casesPerOneMillion": 0
    },
    {
        "country": "Togo",
        "countryInfo": {"iso2": "TG"},
        "cases": 1,
        "todayCases": 0,
        "deaths": 0,
        "todayDeaths": 0,
        "recovered": 0,
        "active": 1,
        "critical": 0,
        "casesPerOneMillion": 0
    }
]
